{
  "$schema": "https://developer.microsoft.com/json-schemas/spfx-build/package-solution.schema.json",
  "solution": {
    "name": "contoso-orders-client-side-solution",
    "id": "093eebef-9dbb-4b13-ba09-4da180bceb6d",
    "version": "1.0.0.0",
    "includeClientSideAssets": true,
    "skipFeatureDeployment": true,
    "isDomainIsolated": false,
    "developer": {
      "name": "Microsoft 365 PnP",
      "websiteUrl": "https://aka.ms/m365pnp",
      "privacyUrl": "",
      "termsOfUseUrl": "",
      "mpnId": "Undefined-1.13.0"
    },
    "webApiPermissionRequests": [
      {
        "appId": "a47390a4-f0cb-42ee-b3de-0a0af6e44f2d",
        "replyUrl": "https://aka.ms/m365pnp",
        "resource": "PnP.Contoso.Orders",
        "scope": "Orders.FullControl"
      }
    ],
    "metadata": {
      "shortDescription": {
        "default": "PnP Contoso Orders sample"
      },
      "longDescription": {
        "default": "PnP Contoso Orders sample"
      },
      "screenshotPaths": [],
      "videoUrl": "",
      "categories": []
    }
  },
  "paths": {
    "zippedPackage": "solution/contoso-orders.sppkg"
  }
}
